arrayviz/__init__.py
arrayviz/animations.py
arrayviz-0.0.1.dist-info/LICENSE
arrayviz-0.0.1.dist-info/METADATA
arrayviz-0.0.1.dist-info/WHEEL
arrayviz-0.0.1.dist-info/top_level.txt
arrayviz-0.0.1.dist-info/RECORD
