Metadata-Version: 2.1
Name: arrayviz
Version: 0.0.1
Summary: A Python package for visualizing array-based algorithms using Manim
Author-email: Aanas Sayed <aanas.sayed@outlook.com>
Maintainer-email: Aanas Sayed <aanas.sayed@outlook.com>
Project-URL: Homepage, https://github.com/aanas-sayed/arrayviz
Project-URL: Documentation, https://github.com/aanas-sayed/arrayviz
Project-URL: Repository, https://github.com/aanas-sayed/arrayviz.git
Project-URL: Issues, https://github.com/aanas-sayed/arrayviz/issues
Keywords: array,visualization,manim,animation
Classifier: Development Status :: 3 - Alpha
Classifier: Programming Language :: Python :: 3
Classifier: Programming Language :: Python :: 3.8
Classifier: Programming Language :: Python :: 3.9
Classifier: Programming Language :: Python :: 3.10
Classifier: Programming Language :: Python :: 3.11
Classifier: Programming Language :: Python :: 3.12
Classifier: License :: OSI Approved :: MIT License
Classifier: Operating System :: OS Independent
Classifier: Intended Audience :: Developers
Classifier: Intended Audience :: Education
Requires-Python: >=3.8
License-File: LICENSE
Requires-Dist: manim >=0.18.0
